parsdantic/__init__.py
parsdantic/parser.py
parsdantic-0.2.0.dist-info/METADATA
parsdantic-0.2.0.dist-info/WHEEL
parsdantic-0.2.0.dist-info/entry_points.txt
parsdantic-0.2.0.dist-info/licenses/LICENSE
parsdantic-0.2.0.dist-info/RECORD
