Metadata-Version: 2.4
Name: parsdantic
Version: 0.2.0
Summary: Parsdantic is a powerful Python package that automatically generates Pydantic models from JSON schemas. Enums support **included**
Author-email: SergiFuster <sergifusterdura@gmail.com>
License-File: LICENSE
Requires-Python: >=3.11
Requires-Dist: jsonref>=1.1.0
Requires-Dist: pydantic>=2.10.6
Requires-Dist: pytest>=8.3.4
